django_polly/__init__.py
django_polly/admin.py
django_polly/apps.py
django_polly/consumers.py
django_polly/consumers_admin.py
django_polly/models.py
django_polly/routing.py
django_polly/urls.py
django_polly/views.py
django_polly/lib/__init__.py
django_polly/lib/connector.py
django_polly/lib/llm_api.py
django_polly/management/__init__.py
django_polly/management/commands/__init__.py
django_polly/management/commands/download_model.py
django_polly/migrations/0001_initial.py
django_polly/migrations/0002_smartconversation_title_alter_message_conversation_and_more.py
django_polly/migrations/0003_alter_smartconversation_title.py
django_polly/migrations/__init__.py
django_polly/static/css/custom.css
django_polly/templates/base.html
django_polly/templates/conversation/access_denied.html
django_polly/templates/conversation/not_found.html
django_polly/templates/conversation/single_chat.html
django_polly/templates/conversation/ws/chat_message.html
django_polly/templates/django_polly/dashboard.html
django_polly/tests/__init__.py
django_polly/tests/settings.py
django_polly/tests/test_admin.py
django_polly/tests/test_configuration.py
django_polly/tests/test_consumers.py
django_polly/tests/test_llm_api.py
django_polly/tests/test_management_commands.py
django_polly/tests/test_models.py
django_polly/tests/test_views.py
django_polly/tests/helpers/__init__.py
django_polly/tests/helpers/asgi.py
docs/__init__.py
docs/conf.py
django_polly-0.0.5.dist-info/LICENSE
django_polly-0.0.5.dist-info/METADATA
django_polly-0.0.5.dist-info/WHEEL
django_polly-0.0.5.dist-info/top_level.txt
django_polly-0.0.5.dist-info/RECORD
