Metadata-Version: 2.1
Name: django-polly
Version: 0.0.5
Summary: A Django app for building parrot configurations
Home-page: https://github.com/pollystack/django-polly
Author: Pollystack Team
Author-email: info@pollystack.com
License: AGPL-3.0
Classifier: Environment :: Web Environment
Classifier: Framework :: Django
Classifier: Framework :: Django :: 3.2
Classifier: Intended Audience :: Developers
Classifier: License :: OSI Approved :: GNU Affero General Public License v3
Classifier: Operating System :: OS Independent
Classifier: Programming Language :: Python
Classifier: Programming Language :: Python :: 3
Classifier: Programming Language :: Python :: 3.8
Classifier: Programming Language :: Python :: 3.9
Classifier: Topic :: Internet :: WWW/HTTP
Classifier: Topic :: Internet :: WWW/HTTP :: Dynamic Content
Classifier: Topic :: Software Development :: Libraries :: Application Frameworks
Classifier: Topic :: Scientific/Engineering :: Artificial Intelligence
License-File: LICENSE
Requires-Dist: Django >=4.0
Requires-Dist: requests
Requires-Dist: tqdm
Requires-Dist: django-json-widget
Requires-Dist: djangorestframework
Requires-Dist: drf-spectacular
Requires-Dist: llama-cpp-python ==0.2.87
Requires-Dist: channels[daphne]
Requires-Dist: asgiref
Provides-Extra: dev
Requires-Dist: pytest ; extra == 'dev'
Requires-Dist: pytest-django ; extra == 'dev'
Requires-Dist: pytest-cov ; extra == 'dev'
Requires-Dist: pytest-asyncio ; extra == 'dev'
Provides-Extra: test
Requires-Dist: pytest ; extra == 'test'
Requires-Dist: pytest-django ; extra == 'test'
Requires-Dist: pytest-asyncio ; extra == 'test'
Requires-Dist: pytest-cov ; extra == 'test'
Requires-Dist: tox ; extra == 'test'
Requires-Dist: coverage ; extra == 'test'
